brainless/DataFrameVectorizer.py
brainless/__init__.py
brainless/_version.py
brainless/predictor.py
brainless/predictor_base.py
brainless/utils.py
brainless/utils_categorical_ensembling.py
brainless/utils_data_cleaning.py
brainless/utils_ensembling.py
brainless/utils_feature_selection.py
brainless/utils_model_training.py
brainless/utils_models.py
brainless/utils_scaling.py
brainless/utils_scoring.py
brainless-2.0.2.dist-info/LICENSE
brainless-2.0.2.dist-info/METADATA
brainless-2.0.2.dist-info/WHEEL
brainless-2.0.2.dist-info/top_level.txt
brainless-2.0.2.dist-info/RECORD
