Metadata-Version: 2.1
Name: brainless
Version: 2.0.2
Summary: Automated Machine Learning for production and analytics
Home-page: https://github.com/darvis-ai/Brainless
Author: Darvis.ai Team
Author-email: loaiabdalslam@gmail.com
License: MIT
Keywords: machine learning,data science,automated machine learning,regressor,regressors,regression,classification,classifiers,classifier,estimators,predictors,XGBoost,Random Forest,sklearn,scikit-learn,analytics,analysts,coefficients,feature importances,darvis-ai,darvis-research,analytics,artificial intelligence,subpredictors,ensembling,stacking,blending,feature engineering,feature extraction,feature selection,production,pandas,dataframes,machinejs,deep learning,tensorflow,deeplearning,lightgbm,
Platform: UNKNOWN
Classifier: Development Status :: 5 - Production/Stable
Classifier: Intended Audience :: Developers
Classifier: Intended Audience :: Information Technology
Classifier: Intended Audience :: Science/Research
Classifier: Topic :: Scientific/Engineering :: Artificial Intelligence
Classifier: Topic :: Scientific/Engineering :: Information Analysis
Classifier: Topic :: Software Development :: Libraries :: Python Modules
Classifier: License :: OSI Approved :: MIT License
Classifier: Programming Language :: Python :: 3
Classifier: Programming Language :: Python :: 3.5
Classifier: Programming Language :: Python :: 3.6
Classifier: Programming Language :: Python :: 3.7
Requires-Dist: coveralls (>=1.5.0)
Requires-Dist: dill (>=0.2.5)
Requires-Dist: h5py (>=2.7.0)
Requires-Dist: lightgbm (>=2.0.11)
Requires-Dist: nose (>=1.3.0)
Requires-Dist: numpy (>=1.11.0)
Requires-Dist: pandas (>=0.18.0)
Requires-Dist: pathos (>=0.2.1)
Requires-Dist: scikit-learn (>=0.18.1)
Requires-Dist: scipy (>=0.14.0)
Requires-Dist: six (>=1.11.0)
Requires-Dist: sklearn-deap2 (>=0.2.1)
Requires-Dist: tabulate (>=0.7.5)
Requires-Dist: tables (>=3.4.0)
